{
  "db_name": "PostgreSQL",
  "query": "\n                INSERT INTO asset (id, status, owner, created_at, updated_at, deleted_at)\n                VALUES ($1, $2, $3, $4, $5, $6)\n                RETURNING id;\n            ",
  "describe": {
    "columns": [
      {
        "ordinal": 0,
        "name": "id",
        "type_info": "Uuid"
      }
    ],
    "parameters": {
      "Left": [
        "Uuid",
        {
          "Custom": {
            "name": "asset_status",
            "kind": {
              "Enum": [
                "init",
                "uploading",
                "available",
                "failed",
                "aborted",
                "deleted"
              ]
            }
          }
        },
        "Uuid",
        "Timestamptz",
        "Timestamptz",
        "Timestamptz"
      ]
    },
    "nullable": [
      false
    ]
  },
  "hash": "e3b8a3007f77035caec5d82068dbd29c504e27cdabb9f53b2fde5cab989d9c65"
}
